[
  {
    "ContainingType": "MazePathFinding.WebApi.Controllers.MazesController",
    "Method": "SubmitMaze",
    "RelativePath": "api/Mazes",
    "HttpMethod": "POST",
    "IsController": true,
    "Order": 0,
    "Parameters": [
      {
        "Name": "mazeRequest",
        "Type": "MazePathFinding.WebApi.Models.MazeRequest",
        "IsRequired": true
      }
    ],
    "ReturnTypes": [
      {
        "Type": "System.Collections.Generic.List\u00601[[System.Int32[], System.Private.CoreLib, Version=8.0.0.0, Culture=neutral, PublicKeyToken=7cec85d7bea7798e]]",
        "MediaTypes": [
          "application/json"
        ],
        "StatusCode": 200
      },
      {
        "Type": "System.Collections.Generic.List\u00601[[System.Int32[], System.Private.CoreLib, Version=8.0.0.0, Culture=neutral, PublicKeyToken=7cec85d7bea7798e]]",
        "MediaTypes": [
          "application/json"
        ],
        "StatusCode": 400
      }
    ]
  },
  {
    "ContainingType": "MazePathFinding.WebApi.Controllers.MazesController",
    "Method": "GetMazes",
    "RelativePath": "api/Mazes",
    "HttpMethod": "GET",
    "IsController": true,
    "Order": 0,
    "Parameters": [],
    "ReturnTypes": [
      {
        "Type": "System.Void",
        "MediaTypes": [],
        "StatusCode": 200
      },
      {
        "Type": "System.String",
        "MediaTypes": [
          "application/json"
        ],
        "StatusCode": 404
      }
    ]
  }
]